refill/__init__.py
refill/core.py
refill/filters.py
refill/pptx.py
refill/spec.py
refill-0.7.dist-info/LICENSE
refill-0.7.dist-info/METADATA
refill-0.7.dist-info/WHEEL
refill-0.7.dist-info/top_level.txt
refill-0.7.dist-info/RECORD
